IGNORE.txt
MANIFEST.in
README.txt
bootstrap.py
buildout.cfg
setup.py
docs/HISTORY.txt
docs/INSTALL.txt
docs/LICENSE.GPL
docs/LICENSE.txt
profiles/base.cfg
profiles/plone3.cfg
profiles/plone4.cfg
src/.DS_Store
src/collective/.DS_Store
src/collective/__init__.py
src/collective.easyslideshow.egg-info/PKG-INFO
src/collective.easyslideshow.egg-info/SOURCES.txt
src/collective.easyslideshow.egg-info/dependency_links.txt
src/collective.easyslideshow.egg-info/entry_points.txt
src/collective.easyslideshow.egg-info/namespace_packages.txt
src/collective.easyslideshow.egg-info/not-zip-safe
src/collective.easyslideshow.egg-info/requires.txt
src/collective.easyslideshow.egg-info/top_level.txt
src/collective/easyslideshow/.DS_Store
src/collective/easyslideshow/README.txt
src/collective/easyslideshow/__init__.py
src/collective/easyslideshow/configure.zcml
src/collective/easyslideshow/events.py
src/collective/easyslideshow/indexers.py
src/collective/easyslideshow/interfaces.py
src/collective/easyslideshow/permissions.zcml
src/collective/easyslideshow/profiles.zcml
src/collective/easyslideshow/setuphandlers.py
src/collective/easyslideshow/subscribers.py
src/collective/easyslideshow/upgrades.py
src/collective/easyslideshow/utils.py
src/collective/easyslideshow/version.txt
src/collective/easyslideshow/Extensions/Install.py
src/collective/easyslideshow/Extensions/__init__.py
src/collective/easyslideshow/browser/__init__.py
src/collective/easyslideshow/browser/configure.zcml
src/collective/easyslideshow/browser/easyslideshow.py
src/collective/easyslideshow/browser/interfaces.py
src/collective/easyslideshow/browser/slideshowmanager.py
src/collective/easyslideshow/browser/slideshowview.py
src/collective/easyslideshow/browser/resources/jquery-cycle.js
src/collective/easyslideshow/browser/resources/slideshow-icon.png
src/collective/easyslideshow/browser/resources/slideshow.css
src/collective/easyslideshow/browser/templates/slideshow_edit_form.pt
src/collective/easyslideshow/browser/templates/slideshow_folder_view.pt
src/collective/easyslideshow/browser/templates/slideshow_macros.pt
src/collective/easyslideshow/locales/collective.easyslideshow.pot
src/collective/easyslideshow/locales/fr/LC_MESSAGES/collective.easyslideshow.po
src/collective/easyslideshow/portlets/__init__.py
src/collective/easyslideshow/portlets/configure.zcml
src/collective/easyslideshow/portlets/slideshow.pt
