Metadata-Version: 1.1
Name: collective.easyslideshow
Version: 3.0
Summary: An easy slideshow solution for Plone
Home-page: http://svn.plone.org/svn/collective/collective.easyslideshow
Author: Six Feet Up, Inc.
Author-email: info@sixfeetup.com
License: GPL
Keywords: plone slideshow
Platform: UNKNOWN
Classifier: Framework :: Plone
Classifier: Programming Language :: Python
Classifier: Topic :: Software Development :: Libraries :: Python Modules
